ProyectoUT2/__init__.py
ProyectoUT2/main.py
proyectout2-0.2.dist-info/METADATA
proyectout2-0.2.dist-info/WHEEL
proyectout2-0.2.dist-info/top_level.txt
proyectout2-0.2.dist-info/RECORD
