Metadata-Version: 2.4
Name: ProyectoUT2
Version: 0.2
Summary: Juego interactivo por pantalla de una simulación de salto con pértiga, en la que puedes entrenar y competir seleccionando los atletas.
Requires-Python: >=3.8
